ftir_framework/__init__.py
ftir_framework/config/__init__.py
ftir_framework/config/settings.py
ftir_framework/core/__init__.py
ftir_framework/core/evaluator.py
ftir_framework/core/explainer.py
ftir_framework/core/pipeline.py
ftir_framework/optimization/__init__.py
ftir_framework/optimization/optuna_optimizer.py
ftir_framework/preprocessing/__init__.py
ftir_framework/preprocessing/baseline.py
ftir_framework/preprocessing/derivatives.py
ftir_framework/preprocessing/normalization.py
ftir_framework/preprocessing/smoothing.py
ftir_framework/preprocessing/truncation.py
ftir_framework/utils/__init__.py
ftir_framework/utils/data_loader.py
ftir_prep-0.1.0.dist-info/licenses/LICENSE
ftir_prep-0.1.0.dist-info/METADATA
ftir_prep-0.1.0.dist-info/WHEEL
ftir_prep-0.1.0.dist-info/top_level.txt
ftir_prep-0.1.0.dist-info/RECORD
