Metadata-Version: 2.4
Name: ftir-prep
Version: 0.1.0
Summary: A framework for designing and evaluating optimal preprocessing pipelines for FTIR spectral data used in classification tasks. It provides modular implementations of common preprocessing techniques and allows automated exploration of preprocessing combinations to enhance model performance.
Home-page: https://github.com/username/ftir-preprocessing-framework
Author: Lucas Mendonça
Author-email: Lucas Mendonça <lucas.mendonca@example.com>
Maintainer-email: Lucas Mendonça <lucas.mendonca@example.com>
License-Expression: MIT
Project-URL: Homepage, https://github.com/lucas-mendonca-andrade/FTIR-Prep
Project-URL: Repository, https://github.com/lucas-mendonca-andrade/FTIR-Prep
Project-URL: Bug Tracker, https://github.com/lucas-mendonca-andrade/FTIR-Prep/issues
Project-URL: Documentation, https://github.com/lucas-mendonca-andrade/FTIR-Prep/docs
Keywords: ftir,spectroscopy,preprocessing,machine-learning,optimization,bioinformatics
Classifier: Development Status :: 3 - Alpha
Classifier: Intended Audience :: Science/Research
Classifier: Topic :: Scientific/Engineering :: Bio-Informatics
Classifier: Topic :: Scientific/Engineering :: Chemistry
Classifier: Programming Language :: Python :: 3
Classifier: Programming Language :: Python :: 3.8
Classifier: Programming Language :: Python :: 3.9
Classifier: Programming Language :: Python :: 3.10
Classifier: Programming Language :: Python :: 3.11
Classifier: Programming Language :: Python :: 3.12
Requires-Python: >=3.8
License-File: LICENSE
Requires-Dist: numpy>=1.20.0
Requires-Dist: scikit-learn>=1.0.0
Requires-Dist: optuna>=3.0.0
Requires-Dist: rampy>=0.1.0
Requires-Dist: PyWavelets>=1.9.0
Requires-Dist: statsmodels>=0.13.0
Requires-Dist: pandas>=1.3.0
Requires-Dist: matplotlib>=3.5.0
Requires-Dist: shap>=0.41.0
Requires-Dist: openpyxl>=3.0.0
Provides-Extra: dev
Requires-Dist: pytest>=6.0; extra == "dev"
Requires-Dist: pytest-cov>=3.0; extra == "dev"
Requires-Dist: black>=22.0; extra == "dev"
Requires-Dist: flake8>=4.0; extra == "dev"
Requires-Dist: mypy>=0.950; extra == "dev"
Provides-Extra: docs
Requires-Dist: sphinx>=4.0; extra == "docs"
Requires-Dist: sphinx-rtd-theme>=1.0; extra == "docs"
Requires-Dist: myst-parser>=0.17; extra == "docs"
Dynamic: author
Dynamic: home-page
Dynamic: license-file
Dynamic: requires-python
